pygeneconverter/__init__.py
pygeneconverter/data.csv
pygeneconverter/pygeneconverter.py
pygeneconverter-0.3.dist-info/METADATA
pygeneconverter-0.3.dist-info/WHEEL
pygeneconverter-0.3.dist-info/top_level.txt
pygeneconverter-0.3.dist-info/RECORD
