Metadata-Version: 2.1
Name: pygeneconverter
Version: 0.3
Summary: A Python package for converting Ensembl IDs to HUGO gene symbols and vice versa.
Requires-Dist: pandas
